bokeh_fastapi/__init__.py
bokeh_fastapi/_version.py
bokeh_fastapi/application.py
bokeh_fastapi/handler.py
bokeh_fastapi-0.1.5.dist-info/licenses/LICENSE
bokeh_fastapi-0.1.5.dist-info/METADATA
bokeh_fastapi-0.1.5.dist-info/WHEEL
bokeh_fastapi-0.1.5.dist-info/top_level.txt
bokeh_fastapi-0.1.5.dist-info/RECORD
