Metadata-Version: 2.4
Name: bokeh_fastapi
Version: 0.1.5
Summary: Compatibility layer between Bokeh and FastAPI
Author-email: Philipp Rudiger <prudiger@anaconda.com>, Philip Meier <pmeier@quansight.com>
License: BSD 3-Clause License
Project-URL: Repository, https://github.com/bokeh/bokeh-fastapi
Requires-Python: >=3.10
License-File: LICENSE
Requires-Dist: bokeh>=2.3.3
Requires-Dist: fastapi>=0.68.0
Requires-Dist: starlette
Requires-Dist: websockets>=10.4
Dynamic: license-file
